unified_parts_processor/__init__.py
unified_parts_processor/db.py
unified_parts_processor/models.py
unified_parts_processor/uploader.py
unified_parts_processor-0.1.0.dist-info/METADATA
unified_parts_processor-0.1.0.dist-info/WHEEL
unified_parts_processor-0.1.0.dist-info/top_level.txt
unified_parts_processor-0.1.0.dist-info/RECORD
