Metadata-Version: 2.4
Name: unified-parts-processor
Version: 0.1.0
Summary: A package to upload Pandas DataFrames into PostgreSQL using ORM
Home-page: https://github.com/yourusername/unified-parts-processor
Author: Your Name
Author-email: your@email.com
License: MIT
Classifier: Programming Language :: Python :: 3
Classifier: License :: OSI Approved :: MIT License
Classifier: Operating System :: OS Independent
Requires-Python: >=3.10
Requires-Dist: pandas
Requires-Dist: sqlalchemy
Requires-Dist: psycopg2
Requires-Dist: environs
Requires-Dist: pytest
